setup.py
gauss_distributions/Binomialdistribution.py
gauss_distributions/Gaussiandistribution.py
gauss_distributions/Generaldistribution.py
gauss_distributions/__init__.py
gauss_distributions.egg-info/PKG-INFO
gauss_distributions.egg-info/SOURCES.txt
gauss_distributions.egg-info/dependency_links.txt
gauss_distributions.egg-info/not-zip-safe
gauss_distributions.egg-info/top_level.txt